google_alerts_mcp/__init__.py
google_alerts_mcp/server.py
google_alerts_mcp-0.1.2.dist-info/METADATA
google_alerts_mcp-0.1.2.dist-info/WHEEL
google_alerts_mcp-0.1.2.dist-info/entry_points.txt
google_alerts_mcp-0.1.2.dist-info/licenses/LICENSE
google_alerts_mcp-0.1.2.dist-info/RECORD
