Metadata-Version: 2.4
Name: google-alerts-mcp
Version: 0.1.2
Summary: Google Alerts MCP Server for fetching topic-based news and information
Project-URL: Homepage, https://github.com/ycrao/google-alerts-mcp
Project-URL: Repository, https://github.com/ycrao/google-alerts-mcp
Project-URL: Issues, https://github.com/ycrao/google-alerts-mcp/issues
Author-email: raoyc <raoyc2009@gmail.com>
License: MIT
License-File: LICENSE
Keywords: google-alerts,mcp,model-context-protocol,news
Classifier: Development Status :: 4 - Beta
Classifier: Intended Audience :: Developers
Classifier: License :: OSI Approved :: MIT License
Classifier: Programming Language :: Python :: 3
Classifier: Programming Language :: Python :: 3.10
Classifier: Programming Language :: Python :: 3.11
Classifier: Programming Language :: Python :: 3.12
Classifier: Topic :: Internet :: WWW/HTTP :: Dynamic Content :: News/Diary
Classifier: Topic :: Software Development :: Libraries :: Python Modules
Requires-Python: >=3.10
Requires-Dist: beautifulsoup4>=4.12.0
Requires-Dist: httpx>=0.25.0
Requires-Dist: mcp>=1.0.0
Requires-Dist: pydantic>=2.0.0
Requires-Dist: selenium>=4.15.0
